pyqt_new_window_handler/__init__.py
pyqt_new_window_handler/newWindowHandler.py
pyqt_new_window_handler-0.0.2.dist-info/LICENSE
pyqt_new_window_handler-0.0.2.dist-info/METADATA
pyqt_new_window_handler-0.0.2.dist-info/WHEEL
pyqt_new_window_handler-0.0.2.dist-info/top_level.txt
pyqt_new_window_handler-0.0.2.dist-info/RECORD
