Metadata-Version: 2.1
Name: pyqt-new-window-handler
Version: 0.0.2
Summary: PyQt QObject type class which operates/handles "New Window" feature
Home-page: https://github.com/yjg30737/pyqt-new-window-handler.git
Author: Jung Gyu Yoon
Author-email: yjg30737@gmail.com
License: MIT
License-File: LICENSE
Requires-Dist: PyQt5 >=5.15
Requires-Dist: pyqt-custom-titlebar-setter >=0.0.1
Requires-Dist: pyqt-custom-titlebar-window >=0.0.1
